CHANGELOG.rst
LICENSE
README.rst
quantdom/__init__.py
quantdom/app.py
quantdom/cli.py
quantdom/lib/__init__.py
quantdom/lib/base.py
quantdom/lib/charts.py
quantdom/lib/const.py
quantdom/lib/loaders.py
quantdom/lib/performance.py
quantdom/lib/portfolio.py
quantdom/lib/strategy.py
quantdom/lib/tables.py
quantdom/lib/utils.py
quantdom/report_rows.json
quantdom/ui.py
quantdom-0.1.1.dist-info/entry_points.txt
quantdom-0.1.1.dist-info/LICENSE
quantdom-0.1.1.dist-info/WHEEL
quantdom-0.1.1.dist-info/METADATA
quantdom-0.1.1.dist-info/RECORD
